[
  {
    "title": ""
  },
  {
    "title": "Я бачу, вас цікавить пітьма",
    "link": "https://www.bookovka.ua/uk/proza/2420335-ya-bachu-vas-cikavit-pitma.html"
  },
  {
    "title": "Вірші з бійниці",
    "link": "https://www.bookovka.ua/uk/khudozhnya-literatura/3395657-virshi-z-bijnici.html"
  },
  {
    "title": "Календар квартальний на 2024 рік на 3 пружини \"Все",
    "link": "https://www.bookovka.ua/uk/kalendari/3470352-kalendar-kvartalnij-na-2024-rik-na-3-pruzhini-vse-bude-ukrayina.html"
  },
  {
    "title": "Якби він був зі мною",
    "link": "https://www.bookovka.ua/uk/khudozhnya-literatura/3486767-yakbi-vin-buv-zi-mnoyu.html"
  },
  {
    "title": "Панк 57",
    "link": "https://www.bookovka.ua/uk/khudozhnya-literatura/3517479-pank-57.html"
  },
  {
    "title": "Дюна (нова суперобкладинка)",
    "link": "https://www.bookovka.ua/uk/fantastika/3531121-dyuna-nova-superobkladinka.html"
  },
  {
    "title": "Місто Кісток"
  },
  {
    "title": "Щодо мови правничої: студії, зібране, словники, документи"
  },
  {
    "title": "Книга ночі"
  },
  {
    "title": "Картина по номерам Рассвет над крышами Парижа 40 х 50 см (KHO2697)"
  },
  {
    "title": "Картина по номерам Страстное утро 40 х 50 см (KHO4573)"
  },
  {
    "title": "Настольная игра Dixit (Диксит)"
  },
  {
    "title": "Рюкзак GLOBBER, синий"
  },
  {
    "title": "Самокат GLOBBER серии PRIMO LIGHTS, красный, колеса с подсветкой, до 50кг, 3+, 3 колеса"
  },
  {
    "title": "Рюкзак \"Bobby Urban Lite\" против кражи, серый"
  },
  {
    "title": "Атака на Титанов. Книга 1\n\n(Исаяма Х., язык: Російська)",
    "link": "https://www.bookovka.ua/uk/khudozhnya-literatura/4064-ataka-na-titanov-kniga-1.html"
  },
  {
    "title": "Токийский гуль: re. Книга 1\n\n(Суи Исида, язык: Російська)",
    "link": "https://www.bookovka.ua/uk/proza/1132913-tokijskij-gul-re-kniga-1.html"
  },
  {
    "title": "Покинь, якщо кохаєш\n\n(Колін Гувер, язык: Українська)",
    "link": "https://www.bookovka.ua/uk/khudozhnya-literatura/75697-pokin-yakshho-kokhayesh.html"
  },
  {
    "title": "П’ять ночей із Фредді. Книга 1: Срібні очі\n\n(Скотт Коутон, язык: Українська)",
    "link": "https://www.bookovka.ua/uk/khudozhnya-literatura/2467235-pyat-nochej-iz-freddi-kniga-1-sribni-ochi.html"
  },
  {
    "title": "Атака на Титанов. Книга 5\n\n(Исаяма Х., язык: Російська)",
    "link": "https://www.bookovka.ua/uk/khudozhnya-literatura/4375-ataka-na-titanov-kniga-5.html"
  },
  {
    "title": "Атака на Титанов. Кн.8\n\n(Хадзимэ Исаяма, язык: Російська)",
    "link": "https://www.bookovka.ua/uk/fentezi/31050-ataka-na-titanovkn8.html"
  },
  {
    "title": "Доця\n\n(Тамара Горіха Зерня, язык: Українська)",
    "link": "https://www.bookovka.ua/uk/proza/2423348-docya.html"
  },
  {
    "title": "Молоко і мед\n\n(Рупи Каур, язык: Українська)",
    "link": "https://www.bookovka.ua/uk/poeziya/101680-moloko-i-med.html"
  },
  {
    "title": "Атака на титанов. Книга 12\n\n(Хадзимэ Исаяма, язык: Російська)",
    "link": "https://www.bookovka.ua/uk/khudozhnya-literatura/51077-ataka-na-titanov-kniga-12.html"
  },
  {
    "title": "Книга 24.02. Щоденник війни\n\n(Андрей Меронык, язык: Українська)",
    "link": "https://www.bookovka.ua/uk/proza/2507954-kniga-2402-shhodennik-vijni.html"
  },
  {
    "title": "Задивляюсь у твої зіниці\n\n(Василь Симоненко, язык: Українська)",
    "link": "https://www.bookovka.ua/uk/khudozhnya-literatura/99060-zadivlyayus-u-tvoyi-zinici.html"
  },
  {
    "title": "Квітнева відьма\n\n(Майгуль Аксельссон, язык: Українська)",
    "link": "https://www.bookovka.ua/uk/proza/1145611-kvitneva-vidma.html"
  },
  {
    "title": ""
  },
  {
    "title": "Я бачу, вас цікавить пітьма",
    "link": "https://www.bookovka.ua/uk/proza/2420335-ya-bachu-vas-cikavit-pitma.html"
  },
  {
    "title": "Вірші з бійниці",
    "link": "https://www.bookovka.ua/uk/khudozhnya-literatura/3395657-virshi-z-bijnici.html"
  },
  {
    "title": "Календар квартальний на 2024 рік на 3 пружини \"Все",
    "link": "https://www.bookovka.ua/uk/kalendari/3470352-kalendar-kvartalnij-na-2024-rik-na-3-pruzhini-vse-bude-ukrayina.html"
  },
  {
    "title": "Якби він був зі мною",
    "link": "https://www.bookovka.ua/uk/khudozhnya-literatura/3486767-yakbi-vin-buv-zi-mnoyu.html"
  },
  {
    "title": "Панк 57",
    "link": "https://www.bookovka.ua/uk/khudozhnya-literatura/3517479-pank-57.html"
  },
  {
    "title": "Дюна (нова суперобкладинка)",
    "link": "https://www.bookovka.ua/uk/fantastika/3531121-dyuna-nova-superobkladinka.html"
  },
  {
    "title": "Місто Кісток"
  },
  {
    "title": "Щодо мови правничої: студії, зібране, словники, документи"
  },
  {
    "title": "Книга ночі"
  },
  {
    "title": "Картина по номерам Рассвет над крышами Парижа 40 х 50 см (KHO2697)"
  },
  {
    "title": "Картина по номерам Страстное утро 40 х 50 см (KHO4573)"
  },
  {
    "title": "Настольная игра Dixit (Диксит)"
  },
  {
    "title": "Рюкзак GLOBBER, синий"
  },
  {
    "title": "Самокат GLOBBER серии PRIMO LIGHTS, красный, колеса с подсветкой, до 50кг, 3+, 3 колеса"
  },
  {
    "title": "Рюкзак \"Bobby Urban Lite\" против кражи, серый"
  },
  {
    "title": "Атака на Титанов. Книга 1\n\n(Исаяма Х., язык: Російська)",
    "link": "https://www.bookovka.ua/uk/khudozhnya-literatura/4064-ataka-na-titanov-kniga-1.html"
  },
  {
    "title": "Токийский гуль: re. Книга 1\n\n(Суи Исида, язык: Російська)",
    "link": "https://www.bookovka.ua/uk/proza/1132913-tokijskij-gul-re-kniga-1.html"
  },
  {
    "title": "Покинь, якщо кохаєш\n\n(Колін Гувер, язык: Українська)",
    "link": "https://www.bookovka.ua/uk/khudozhnya-literatura/75697-pokin-yakshho-kokhayesh.html"
  },
  {
    "title": "П’ять ночей із Фредді. Книга 1: Срібні очі\n\n(Скотт Коутон, язык: Українська)",
    "link": "https://www.bookovka.ua/uk/khudozhnya-literatura/2467235-pyat-nochej-iz-freddi-kniga-1-sribni-ochi.html"
  },
  {
    "title": "Атака на Титанов. Книга 5\n\n(Исаяма Х., язык: Російська)",
    "link": "https://www.bookovka.ua/uk/khudozhnya-literatura/4375-ataka-na-titanov-kniga-5.html"
  },
  {
    "title": "Атака на Титанов. Кн.8\n\n(Хадзимэ Исаяма, язык: Російська)",
    "link": "https://www.bookovka.ua/uk/fentezi/31050-ataka-na-titanovkn8.html"
  },
  {
    "title": "Доця\n\n(Тамара Горіха Зерня, язык: Українська)",
    "link": "https://www.bookovka.ua/uk/proza/2423348-docya.html"
  },
  {
    "title": "Молоко і мед\n\n(Рупи Каур, язык: Українська)",
    "link": "https://www.bookovka.ua/uk/poeziya/101680-moloko-i-med.html"
  },
  {
    "title": "Атака на титанов. Книга 12\n\n(Хадзимэ Исаяма, язык: Російська)",
    "link": "https://www.bookovka.ua/uk/khudozhnya-literatura/51077-ataka-na-titanov-kniga-12.html"
  },
  {
    "title": "Книга 24.02. Щоденник війни\n\n(Андрей Меронык, язык: Українська)",
    "link": "https://www.bookovka.ua/uk/proza/2507954-kniga-2402-shhodennik-vijni.html"
  },
  {
    "title": "Задивляюсь у твої зіниці\n\n(Василь Симоненко, язык: Українська)",
    "link": "https://www.bookovka.ua/uk/khudozhnya-literatura/99060-zadivlyayus-u-tvoyi-zinici.html"
  },
  {
    "title": "Квітнева відьма\n\n(Майгуль Аксельссон, язык: Українська)",
    "link": "https://www.bookovka.ua/uk/proza/1145611-kvitneva-vidma.html"
  },
  {
    "title": ""
  },
  {
    "title": "Я бачу, вас цікавить пітьма",
    "link": "https://www.bookovka.ua/uk/proza/2420335-ya-bachu-vas-cikavit-pitma.html"
  },
  {
    "title": "Вірші з бійниці",
    "link": "https://www.bookovka.ua/uk/khudozhnya-literatura/3395657-virshi-z-bijnici.html"
  },
  {
    "title": "Календар квартальний на 2024 рік на 3 пружини \"Все",
    "link": "https://www.bookovka.ua/uk/kalendari/3470352-kalendar-kvartalnij-na-2024-rik-na-3-pruzhini-vse-bude-ukrayina.html"
  },
  {
    "title": "Якби він був зі мною",
    "link": "https://www.bookovka.ua/uk/khudozhnya-literatura/3486767-yakbi-vin-buv-zi-mnoyu.html"
  },
  {
    "title": "Панк 57",
    "link": "https://www.bookovka.ua/uk/khudozhnya-literatura/3517479-pank-57.html"
  },
  {
    "title": "Дюна (нова суперобкладинка)",
    "link": "https://www.bookovka.ua/uk/fantastika/3531121-dyuna-nova-superobkladinka.html"
  },
  {
    "title": "Місто Кісток"
  },
  {
    "title": "Щодо мови правничої: студії, зібране, словники, документи"
  },
  {
    "title": "Книга ночі"
  },
  {
    "title": "Картина по номерам Рассвет над крышами Парижа 40 х 50 см (KHO2697)"
  },
  {
    "title": "Картина по номерам Страстное утро 40 х 50 см (KHO4573)"
  },
  {
    "title": "Настольная игра Dixit (Диксит)"
  },
  {
    "title": "Рюкзак GLOBBER, синий"
  },
  {
    "title": "Самокат GLOBBER серии PRIMO LIGHTS, красный, колеса с подсветкой, до 50кг, 3+, 3 колеса"
  },
  {
    "title": "Рюкзак \"Bobby Urban Lite\" против кражи, серый"
  },
  {
    "title": "Атака на Титанов. Книга 1\n\n(Исаяма Х., язык: Російська)",
    "link": "https://www.bookovka.ua/uk/khudozhnya-literatura/4064-ataka-na-titanov-kniga-1.html"
  },
  {
    "title": "Токийский гуль: re. Книга 1\n\n(Суи Исида, язык: Російська)",
    "link": "https://www.bookovka.ua/uk/proza/1132913-tokijskij-gul-re-kniga-1.html"
  },
  {
    "title": "Покинь, якщо кохаєш\n\n(Колін Гувер, язык: Українська)",
    "link": "https://www.bookovka.ua/uk/khudozhnya-literatura/75697-pokin-yakshho-kokhayesh.html"
  },
  {
    "title": "П’ять ночей із Фредді. Книга 1: Срібні очі\n\n(Скотт Коутон, язык: Українська)",
    "link": "https://www.bookovka.ua/uk/khudozhnya-literatura/2467235-pyat-nochej-iz-freddi-kniga-1-sribni-ochi.html"
  },
  {
    "title": "Атака на Титанов. Книга 5\n\n(Исаяма Х., язык: Російська)",
    "link": "https://www.bookovka.ua/uk/khudozhnya-literatura/4375-ataka-na-titanov-kniga-5.html"
  },
  {
    "title": "Атака на Титанов. Кн.8\n\n(Хадзимэ Исаяма, язык: Російська)",
    "link": "https://www.bookovka.ua/uk/fentezi/31050-ataka-na-titanovkn8.html"
  },
  {
    "title": "Доця\n\n(Тамара Горіха Зерня, язык: Українська)",
    "link": "https://www.bookovka.ua/uk/proza/2423348-docya.html"
  },
  {
    "title": "Молоко і мед\n\n(Рупи Каур, язык: Українська)",
    "link": "https://www.bookovka.ua/uk/poeziya/101680-moloko-i-med.html"
  },
  {
    "title": "Атака на титанов. Книга 12\n\n(Хадзимэ Исаяма, язык: Російська)",
    "link": "https://www.bookovka.ua/uk/khudozhnya-literatura/51077-ataka-na-titanov-kniga-12.html"
  },
  {
    "title": "Книга 24.02. Щоденник війни\n\n(Андрей Меронык, язык: Українська)",
    "link": "https://www.bookovka.ua/uk/proza/2507954-kniga-2402-shhodennik-vijni.html"
  },
  {
    "title": "Задивляюсь у твої зіниці\n\n(Василь Симоненко, язык: Українська)",
    "link": "https://www.bookovka.ua/uk/khudozhnya-literatura/99060-zadivlyayus-u-tvoyi-zinici.html"
  },
  {
    "title": "Квітнева відьма\n\n(Майгуль Аксельссон, язык: Українська)",
    "link": "https://www.bookovka.ua/uk/proza/1145611-kvitneva-vidma.html"
  },
  {
    "title": ""
  },
  {
    "title": "Я бачу, вас цікавить пітьма",
    "link": "https://www.bookovka.ua/uk/proza/2420335-ya-bachu-vas-cikavit-pitma.html"
  },
  {
    "title": "Вірші з бійниці",
    "link": "https://www.bookovka.ua/uk/khudozhnya-literatura/3395657-virshi-z-bijnici.html"
  },
  {
    "title": "Календар квартальний на 2024 рік на 3 пружини \"Все",
    "link": "https://www.bookovka.ua/uk/kalendari/3470352-kalendar-kvartalnij-na-2024-rik-na-3-pruzhini-vse-bude-ukrayina.html"
  },
  {
    "title": "Якби він був зі мною",
    "link": "https://www.bookovka.ua/uk/khudozhnya-literatura/3486767-yakbi-vin-buv-zi-mnoyu.html"
  },
  {
    "title": "Панк 57",
    "link": "https://www.bookovka.ua/uk/khudozhnya-literatura/3517479-pank-57.html"
  },
  {
    "title": "Дюна (нова суперобкладинка)",
    "link": "https://www.bookovka.ua/uk/fantastika/3531121-dyuna-nova-superobkladinka.html"
  },
  {
    "title": "Місто Кісток"
  },
  {
    "title": "Щодо мови правничої: студії, зібране, словники, документи"
  },
  {
    "title": "Книга ночі"
  },
  {
    "title": "Картина по номерам Рассвет над крышами Парижа 40 х 50 см (KHO2697)"
  },
  {
    "title": "Картина по номерам Страстное утро 40 х 50 см (KHO4573)"
  },
  {
    "title": "Настольная игра Dixit (Диксит)"
  },
  {
    "title": "Рюкзак GLOBBER, синий"
  },
  {
    "title": "Самокат GLOBBER серии PRIMO LIGHTS, красный, колеса с подсветкой, до 50кг, 3+, 3 колеса"
  },
  {
    "title": "Рюкзак \"Bobby Urban Lite\" против кражи, серый"
  },
  {
    "title": "Атака на Титанов. Книга 1\n\n(Исаяма Х., язык: Російська)",
    "link": "https://www.bookovka.ua/uk/khudozhnya-literatura/4064-ataka-na-titanov-kniga-1.html"
  },
  {
    "title": "Токийский гуль: re. Книга 1\n\n(Суи Исида, язык: Російська)",
    "link": "https://www.bookovka.ua/uk/proza/1132913-tokijskij-gul-re-kniga-1.html"
  },
  {
    "title": "Покинь, якщо кохаєш\n\n(Колін Гувер, язык: Українська)",
    "link": "https://www.bookovka.ua/uk/khudozhnya-literatura/75697-pokin-yakshho-kokhayesh.html"
  },
  {
    "title": "П’ять ночей із Фредді. Книга 1: Срібні очі\n\n(Скотт Коутон, язык: Українська)",
    "link": "https://www.bookovka.ua/uk/khudozhnya-literatura/2467235-pyat-nochej-iz-freddi-kniga-1-sribni-ochi.html"
  },
  {
    "title": "Атака на Титанов. Книга 5\n\n(Исаяма Х., язык: Російська)",
    "link": "https://www.bookovka.ua/uk/khudozhnya-literatura/4375-ataka-na-titanov-kniga-5.html"
  },
  {
    "title": "Атака на Титанов. Кн.8\n\n(Хадзимэ Исаяма, язык: Російська)",
    "link": "https://www.bookovka.ua/uk/fentezi/31050-ataka-na-titanovkn8.html"
  },
  {
    "title": "Доця\n\n(Тамара Горіха Зерня, язык: Українська)",
    "link": "https://www.bookovka.ua/uk/proza/2423348-docya.html"
  },
  {
    "title": "Молоко і мед\n\n(Рупи Каур, язык: Українська)",
    "link": "https://www.bookovka.ua/uk/poeziya/101680-moloko-i-med.html"
  },
  {
    "title": "Атака на титанов. Книга 12\n\n(Хадзимэ Исаяма, язык: Російська)",
    "link": "https://www.bookovka.ua/uk/khudozhnya-literatura/51077-ataka-na-titanov-kniga-12.html"
  },
  {
    "title": "Книга 24.02. Щоденник війни\n\n(Андрей Меронык, язык: Українська)",
    "link": "https://www.bookovka.ua/uk/proza/2507954-kniga-2402-shhodennik-vijni.html"
  },
  {
    "title": "Задивляюсь у твої зіниці\n\n(Василь Симоненко, язык: Українська)",
    "link": "https://www.bookovka.ua/uk/khudozhnya-literatura/99060-zadivlyayus-u-tvoyi-zinici.html"
  },
  {
    "title": "Квітнева відьма\n\n(Майгуль Аксельссон, язык: Українська)",
    "link": "https://www.bookovka.ua/uk/proza/1145611-kvitneva-vidma.html"
  }
]